DJModels-0.0.6.data/scripts/django-admin.py
djmodels/__init__.py
djmodels/__main__.py
djmodels/apps/__init__.py
djmodels/apps/config.py
djmodels/apps/registry.py
djmodels/bin/django-admin.py
djmodels/conf/__init__.py
djmodels/conf/global_settings.py
djmodels/conf/app_template/__init__.py-tpl
djmodels/conf/app_template/admin.py-tpl
djmodels/conf/app_template/apps.py-tpl
djmodels/conf/app_template/models.py-tpl
djmodels/conf/app_template/tests.py-tpl
djmodels/conf/app_template/views.py-tpl
djmodels/conf/app_template/migrations/__init__.py-tpl
djmodels/conf/locale/__init__.py
djmodels/conf/locale/af/LC_MESSAGES/django.mo
djmodels/conf/locale/af/LC_MESSAGES/django.po
djmodels/conf/locale/ar/__init__.py
djmodels/conf/locale/ar/formats.py
djmodels/conf/locale/ar/LC_MESSAGES/django.mo
djmodels/conf/locale/ar/LC_MESSAGES/django.po
djmodels/conf/locale/ast/LC_MESSAGES/django.mo
djmodels/conf/locale/ast/LC_MESSAGES/django.po
djmodels/conf/locale/az/__init__.py
djmodels/conf/locale/az/formats.py
djmodels/conf/locale/az/LC_MESSAGES/django.mo
djmodels/conf/locale/az/LC_MESSAGES/django.po
djmodels/conf/locale/be/LC_MESSAGES/django.mo
djmodels/conf/locale/be/LC_MESSAGES/django.po
djmodels/conf/locale/bg/__init__.py
djmodels/conf/locale/bg/formats.py
djmodels/conf/locale/bg/LC_MESSAGES/django.mo
djmodels/conf/locale/bg/LC_MESSAGES/django.po
djmodels/conf/locale/bn/__init__.py
djmodels/conf/locale/bn/formats.py
djmodels/conf/locale/bn/LC_MESSAGES/django.mo
djmodels/conf/locale/bn/LC_MESSAGES/django.po
djmodels/conf/locale/br/LC_MESSAGES/django.mo
djmodels/conf/locale/br/LC_MESSAGES/django.po
djmodels/conf/locale/bs/__init__.py
djmodels/conf/locale/bs/formats.py
djmodels/conf/locale/bs/LC_MESSAGES/django.mo
djmodels/conf/locale/bs/LC_MESSAGES/django.po
djmodels/conf/locale/ca/__init__.py
djmodels/conf/locale/ca/formats.py
djmodels/conf/locale/ca/LC_MESSAGES/django.mo
djmodels/conf/locale/ca/LC_MESSAGES/django.po
djmodels/conf/locale/cs/__init__.py
djmodels/conf/locale/cs/formats.py
DJModels-0.0.6.dist-info/LICENSE
DJModels-0.0.6.dist-info/METADATA
DJModels-0.0.6.dist-info/WHEEL
DJModels-0.0.6.dist-info/entry_points.txt
DJModels-0.0.6.dist-info/top_level.txt
DJModels-0.0.6.dist-info/RECORD
