Metadata-Version: 2.1
Name: DJModels
Version: 0.0.6
Summary: Use Django Models in any Python Web Framework
Home-page: https://github.com/iMerica/dj-models
Author: @iMerica
License: BSD
Project-URL: Documentation, https://github.com/iMerica/dj-models
Project-URL: Source, https://github.com/iMerica/dj-models
Project-URL: Tracker, https://github.com/iMerica/dj-models
Platform: UNKNOWN
Classifier: Development Status :: 2 - Pre-Alpha
Classifier: Environment :: Web Environment
Classifier: Framework :: Django
Classifier: Framework :: Flask
Classifier: Intended Audience :: Developers
Classifier: License :: OSI Approved :: BSD License
Classifier: Operating System :: OS Independent
Classifier: Programming Language :: Python
Classifier: Programming Language :: Python :: 3
Classifier: Programming Language :: Python :: 3.5
Classifier: Programming Language :: Python :: 3.6
Classifier: Programming Language :: Python :: 3.7
Classifier: Programming Language :: Python :: 3 :: Only
Classifier: Topic :: Internet :: WWW/HTTP
Classifier: Topic :: Internet :: WWW/HTTP :: Dynamic Content
Classifier: Topic :: Software Development :: Libraries :: Application Frameworks
Classifier: Topic :: Software Development :: Libraries :: Python Modules
Classifier: Topic :: Database :: Database Engines/Servers
Requires-Python: >=3.5
Requires-Dist: pytz
Requires-Dist: psycopg2
Provides-Extra: argon2
Requires-Dist: argon2-cffi (>=16.1.0) ; extra == 'argon2'
Provides-Extra: bcrypt
Requires-Dist: bcrypt ; extra == 'bcrypt'
